pyppl_strict.py
pyppl_strict-0.0.7.dist-info/entry_points.txt
pyppl_strict-0.0.7.dist-info/LICENSE
pyppl_strict-0.0.7.dist-info/WHEEL
pyppl_strict-0.0.7.dist-info/METADATA
pyppl_strict-0.0.7.dist-info/RECORD
